{
  "timestamp": "20250423_171207",
  "api_url": "https://flink.xxx.com",
  "jobs": [
    {
      "jid": "83626907a5d44996ccd18804d31fd9ed",
      "name": "last_list_tag",
      "state": "RUNNING",
      "start-time": 1744602702429,
      "end-time": -1,
      "duration": 796825378,
      "last-modification": 1744602712116,
      "tasks": {
        "total": 4,
        "created": 0,
        "scheduled": 0,
        "deploying": 0,
        "running": 4,
        "finished": 0,
        "canceling": 0,
        "canceled": 0,
        "failed": 0,
        "reconciling": 0,
        "initializing": 0
      }
    },
    {
      "jid": "105e70197f2a44997a98080bfbe4c803",
      "name": "player_20250331_tag_task",
      "state": "RUNNING",
      "start-time": 1744603013511,
      "end-time": -1,
      "duration": 796514296,
      "last-modification": 1744603019114,
      "tasks": {
        "total": 1,
        "created": 0,
        "scheduled": 0,
        "deploying": 0,
        "running": 1,
        "finished": 0,
        "canceling": 0,
        "canceled": 0,
        "failed": 0,
        "reconciling": 0,
        "initializing": 0
      }
    },
    {
      "jid": "02bf9f29f83d771c1c4dd3c31f4368f8",
      "name": "ludo_rank_task",
      "state": "RUNNING",
      "start-time": 1744602662101,
      "end-time": -1,
      "duration": 796865707,
      "last-modification": 1744602683432,
      "tasks": {
        "total": 16,
        "created": 0,
        "scheduled": 0,
        "deploying": 0,
        "running": 16,
        "finished": 0,
        "canceling": 0,
        "canceled": 0,
        "failed": 0,
        "reconciling": 0,
        "initializing": 0
      }
    },
    {
      "jid": "472ab28c439214412330d50e3c9afa55",
      "name": "Live_task",
      "state": "RUNNING",
      "start-time": 1744602740619,
      "end-time": -1,
      "duration": 796787189,
      "last-modification": 1744602749522,
      "tasks": {
        "total": 8,
        "created": 0,
        "scheduled": 0,
        "deploying": 0,
        "running": 8,
        "finished": 0,
        "canceling": 0,
        "canceled": 0,
        "failed": 0,
        "reconciling": 0,
        "initializing": 0
      }
    },
    {
      "jid": "022791e7d4967dbaf5f2f1bbbf7863d4",
      "name": "new_in_user_tag_task",
      "state": "RUNNING",
      "start-time": 1744602683263,
      "end-time": -1,
      "duration": 796844545,
      "last-modification": 1744602697376,
      "tasks": {
        "total": 4,
        "created": 0,
        "scheduled": 0,
        "deploying": 0,
        "running": 4,
        "finished": 0,
        "canceling": 0,
        "canceled": 0,
        "failed": 0,
        "reconciling": 0,
        "initializing": 0
      }
    },
    {
      "jid": "66952c5ddef6ef9eda65dabd49b7bec5",
      "name": "xxxetl_marketing_job",
      "state": "RUNNING",
      "start-time": 1745282813128,
      "end-time": -1,
      "duration": 116714680,
      "last-modification": 1745282826373,
      "tasks": {
        "total": 4,
        "created": 0,
        "scheduled": 0,
        "deploying": 0,
        "running": 4,
        "finished": 0,
        "canceling": 0,
        "canceled": 0,
        "failed": 0,
        "reconciling": 0,
        "initializing": 0
      }
    },
    {
      "jid": "2be728b53e0ab54bca3d6e08e190063a",
      "name": "lucky_20250414_task",
      "state": "RUNNING",
      "start-time": 1744602992722,
      "end-time": -1,
      "duration": 796535086,
      "last-modification": 1744602999783,
      "tasks": {
        "total": 4,
        "created": 0,
        "scheduled": 0,
        "deploying": 0,
        "running": 4,
        "finished": 0,
        "canceling": 0,
        "canceled": 0,
        "failed": 0,
        "reconciling": 0,
        "initializing": 0
      }
    },
    {
      "jid": "e15cbe4e65cd62d2077fa475c45fa9d5",
      "name": "weekly_gold_task",
      "state": "RUNNING",
      "start-time": 1744602931645,
      "end-time": -1,
      "duration": 796596163,
      "last-modification": 1744602942195,
      "tasks": {
        "total": 9,
        "created": 0,
        "scheduled": 0,
        "deploying": 0,
        "running": 9,
        "finished": 0,
        "canceling": 0,
        "canceled": 0,
        "failed": 0,
        "reconciling": 0,
        "initializing": 0
      }
    },
    {
      "jid": "4946897297fd6504846ff30cf4fc8add",
      "name": "inPattern_20250322_tag_task",
      "state": "RUNNING",
      "start-time": 1744603313554,
      "end-time": -1,
      "duration": 796214256,
      "last-modification": 1744603320212,
      "tasks": {
        "total": 2,
        "created": 0,
        "scheduled": 0,
        "deploying": 0,
        "running": 2,
        "finished": 0,
        "canceling": 0,
        "canceled": 0,
        "failed": 0,
        "reconciling": 0,
        "initializing": 0
      }
    },
    {
      "jid": "3cfa5d6dfe5f36bcfcbcb17ae97a1dc7",
      "name": "player_20250331_task",
      "state": "RUNNING",
      "start-time": 1744789425355,
      "end-time": -1,
      "duration": 610102454,
      "last-modification": 1744789434559,
      "tasks": {
        "total": 9,
        "created": 0,
        "scheduled": 0,
        "deploying": 0,
        "running": 9,
        "finished": 0,
        "canceling": 0,
        "canceled": 0,
        "failed": 0,
        "reconciling": 0,
        "initializing": 0
      }
    },
    {
      "jid": "fba96528db0bee03d01077b99bee45de",
      "name": "mega_20250409_task",
      "state": "RUNNING",
      "start-time": 1744603479536,
      "end-time": -1,
      "duration": 796048272,
      "last-modification": 1744603485732,
      "tasks": {
        "total": 2,
        "created": 0,
        "scheduled": 0,
        "deploying": 0,
        "running": 2,
        "finished": 0,
        "canceling": 0,
        "canceled": 0,
        "failed": 0,
        "reconciling": 0,
        "initializing": 0
      }
    },
    {
      "jid": "14843d6af8466e55bd562ac440cfdeb1",
      "name": "gameKingWeek_20250331_task",
      "state": "RUNNING",
      "start-time": 1744603069350,
      "end-time": -1,
      "duration": 796458458,
      "last-modification": 1744603080926,
      "tasks": {
        "total": 9,
        "created": 0,
        "scheduled": 0,
        "deploying": 0,
        "running": 9,
        "finished": 0,
        "canceling": 0,
        "canceled": 0,
        "failed": 0,
        "reconciling": 0,
        "initializing": 0
      }
    },
    {
      "jid": "d96685986d4dde69ff758b895abd638a",
      "name": "medal_task",
      "state": "RUNNING",
      "start-time": 1745397021608,
      "end-time": -1,
      "duration": 2506202,
      "last-modification": 1745397042249,
      "tasks": {
        "total": 4,
        "created": 0,
        "scheduled": 0,
        "deploying": 0,
        "running": 4,
        "finished": 0,
        "canceling": 0,
        "canceled": 0,
        "failed": 0,
        "reconciling": 0,
        "initializing": 0
      }
    },
    {
      "jid": "e077db88f5d4dcf86e1cc444a420a3bf",
      "name": "common_etl_job",
      "state": "RUNNING",
      "start-time": 1745282830878,
      "end-time": -1,
      "duration": 116696930,
      "last-modification": 1745282841531,
      "tasks": {
        "total": 10,
        "created": 0,
        "scheduled": 0,
        "deploying": 0,
        "running": 10,
        "finished": 0,
        "canceling": 0,
        "canceled": 0,
        "failed": 0,
        "reconciling": 0,
        "initializing": 0
      }
    },
    {
      "jid": "23b8b4d9acf9dd91f9ba948c2545ad63",
      "name": "user_tag_task",
      "state": "RUNNING",
      "start-time": 1744603354603,
      "end-time": -1,
      "duration": 796173206,
      "last-modification": 1744603358343,
      "tasks": {
        "total": 2,
        "created": 0,
        "scheduled": 0,
        "deploying": 0,
        "running": 2,
        "finished": 0,
        "canceling": 0,
        "canceled": 0,
        "failed": 0,
        "reconciling": 0,
        "initializing": 0
      }
    },
    {
      "jid": "99e87950532b748a4c3fdafb81afbd6e",
      "name": "user_statistics_balance_task",
      "state": "RUNNING",
      "start-time": 1744603373623,
      "end-time": -1,
      "duration": 796154185,
      "last-modification": 1744603389431,
      "tasks": {
        "total": 3,
        "created": 0,
        "scheduled": 0,
        "deploying": 0,
        "running": 3,
        "finished": 0,
        "canceling": 0,
        "canceled": 0,
        "failed": 0,
        "reconciling": 0,
        "initializing": 0
      }
    },
    {
      "jid": "bfb8a68cc9fedad400bd83338c067d0b",
      "name": "user_statistics_balance_task",
      "state": "RUNNING",
      "start-time": 1744603405319,
      "end-time": -1,
      "duration": 796122491,
      "last-modification": 1744603414004,
      "tasks": {
        "total": 3,
        "created": 0,
        "scheduled": 0,
        "deploying": 0,
        "running": 3,
        "finished": 0,
        "canceling": 0,
        "canceled": 0,
        "failed": 0,
        "reconciling": 0,
        "initializing": 0
      }
    },
    {
      "jid": "8faf44e5b22641592019931a31c91060",
      "name": "talent_live_duration_gift_mq_flink",
      "state": "RUNNING",
      "start-time": 1744603774691,
      "end-time": -1,
      "duration": 795753118,
      "last-modification": 1744603797460,
      "tasks": {
        "total": 14,
        "created": 0,
        "scheduled": 0,
        "deploying": 0,
        "running": 14,
        "finished": 0,
        "canceling": 0,
        "canceled": 0,
        "failed": 0,
        "reconciling": 0,
        "initializing": 0
      }
    },
    {
      "jid": "d90208005b32eac7d73ef3f71b05781a",
      "name": "talent_20250401_task",
      "state": "RUNNING",
      "start-time": 1744602911620,
      "end-time": -1,
      "duration": 796616189,
      "last-modification": 1744602918813,
      "tasks": {
        "total": 3,
        "created": 0,
        "scheduled": 0,
        "deploying": 0,
        "running": 3,
        "finished": 0,
        "canceling": 0,
        "canceled": 0,
        "failed": 0,
        "reconciling": 0,
        "initializing": 0
      }
    },
    {
      "jid": "ba1d7f6755da32bb78a2fc5e71a2dbe7",
      "name": "honorAgent_20250401_task",
      "state": "RUNNING",
      "start-time": 1744603442765,
      "end-time": -1,
      "duration": 796085044,
      "last-modification": 1744603448650,
      "tasks": {
        "total": 4,
        "created": 0,
        "scheduled": 0,
        "deploying": 0,
        "running": 4,
        "finished": 0,
        "canceling": 0,
        "canceled": 0,
        "failed": 0,
        "reconciling": 0,
        "initializing": 0
      }
    },
    {
      "jid": "6405f984c065074c6c07729f2b9dde0e",
      "name": "inPattern_20250322_task",
      "state": "RUNNING",
      "start-time": 1744602876260,
      "end-time": -1,
      "duration": 796651549,
      "last-modification": 1744602883105,
      "tasks": {
        "total": 3,
        "created": 0,
        "scheduled": 0,
        "deploying": 0,
        "running": 3,
        "finished": 0,
        "canceling": 0,
        "canceled": 0,
        "failed": 0,
        "reconciling": 0,
        "initializing": 0
      }
    },
    {
      "jid": "8c6baf680d68b9b72d4f049c90b8989b",
      "name": "daily_task_task",
      "state": "RUNNING",
      "start-time": 1744602953182,
      "end-time": -1,
      "duration": 796574628,
      "last-modification": 1744602970517,
      "tasks": {
        "total": 27,
        "created": 0,
        "scheduled": 0,
        "deploying": 0,
        "running": 27,
        "finished": 0,
        "canceling": 0,
        "canceled": 0,
        "failed": 0,
        "reconciling": 0,
        "initializing": 0
      }
    },
    {
      "jid": "8148d1212c7ecb9e275a52aea242600e",
      "name": "agent_reward_task",
      "state": "RUNNING",
      "start-time": 1744602721253,
      "end-time": -1,
      "duration": 796806556,
      "last-modification": 1744602726888,
      "tasks": {
        "total": 2,
        "created": 0,
        "scheduled": 0,
        "deploying": 0,
        "running": 2,
        "finished": 0,
        "canceling": 0,
        "canceled": 0,
        "failed": 0,
        "reconciling": 0,
        "initializing": 0
      }
    },
    {
      "jid": "77778052e588fae929ef455b391499d1",
      "name": "gameKing_20250401_task",
      "state": "RUNNING",
      "start-time": 1744603500156,
      "end-time": -1,
      "duration": 796027653,
      "last-modification": 1744603512466,
      "tasks": {
        "total": 9,
        "created": 0,
        "scheduled": 0,
        "deploying": 0,
        "running": 9,
        "finished": 0,
        "canceling": 0,
        "canceled": 0,
        "failed": 0,
        "reconciling": 0,
        "initializing": 0
      }
    },
    {
      "jid": "6c8f4b2b70c78fbfa09eca4b8baf7d90",
      "name": "preference_type_task",
      "state": "RUNNING",
      "start-time": 1744603461315,
      "end-time": -1,
      "duration": 796066494,
      "last-modification": 1744603472586,
      "tasks": {
        "total": 5,
        "created": 0,
        "scheduled": 0,
        "deploying": 0,
        "running": 5,
        "finished": 0,
        "canceling": 0,
        "canceled": 0,
        "failed": 0,
        "reconciling": 0,
        "initializing": 0
      }
    },
    {
      "jid": "0437cafbfeef9af39ff223abba5c6462",
      "name": "weekly_bean_task",
      "state": "RUNNING",
      "start-time": 1744603164762,
      "end-time": -1,
      "duration": 796363048,
      "last-modification": 1744603173587,
      "tasks": {
        "total": 9,
        "created": 0,
        "scheduled": 0,
        "deploying": 0,
        "running": 9,
        "finished": 0,
        "canceling": 0,
        "canceled": 0,
        "failed": 0,
        "reconciling": 0,
        "initializing": 0
      }
    },
    {
      "jid": "ca5af6b70d1154a715c6d54860cc3122",
      "name": "first_charge_task_task",
      "state": "RUNNING",
      "start-time": 1744603145613,
      "end-time": -1,
      "duration": 796382196,
      "last-modification": 1744603150596,
      "tasks": {
        "total": 2,
        "created": 0,
        "scheduled": 0,
        "deploying": 0,
        "running": 2,
        "finished": 0,
        "canceling": 0,
        "canceled": 0,
        "failed": 0,
        "reconciling": 0,
        "initializing": 0
      }
    },
    {
      "jid": "9330fbdafef6428de1e94e1ca90ab3d5",
      "name": "recharge_guide_popup2_task",
      "state": "RUNNING",
      "start-time": 1744603257965,
      "end-time": -1,
      "duration": 796269844,
      "last-modification": 1744603261353,
      "tasks": {
        "total": 1,
        "created": 0,
        "scheduled": 0,
        "deploying": 0,
        "running": 1,
        "finished": 0,
        "canceling": 0,
        "canceled": 0,
        "failed": 0,
        "reconciling": 0,
        "initializing": 0
      }
    },
    {
      "jid": "5e02ae9444eec57201ce5d125a8099ea",
      "name": "mission_etl_job",
      "state": "RUNNING",
      "start-time": 1745282882197,
      "end-time": -1,
      "duration": 116645612,
      "last-modification": 1745282896248,
      "tasks": {
        "total": 6,
        "created": 0,
        "scheduled": 0,
        "deploying": 0,
        "running": 6,
        "finished": 0,
        "canceling": 0,
        "canceled": 0,
        "failed": 0,
        "reconciling": 0,
        "initializing": 0
      }
    },
    {
      "jid": "1b0f88aeba33449bf8e649f17d0f7f51",
      "name": "new_user_task",
      "state": "RUNNING",
      "start-time": 1744603088973,
      "end-time": -1,
      "duration": 796438836,
      "last-modification": 1744603101767,
      "tasks": {
        "total": 16,
        "created": 0,
        "scheduled": 0,
        "deploying": 0,
        "running": 16,
        "finished": 0,
        "canceling": 0,
        "canceled": 0,
        "failed": 0,
        "reconciling": 0,
        "initializing": 0
      }
    },
    {
      "jid": "f09d2c6f1f3ef8da714cd6d9bb27c5e5",
      "name": "wealthWeek_20250407_task",
      "state": "RUNNING",
      "start-time": 1744602838445,
      "end-time": -1,
      "duration": 796689365,
      "last-modification": 1744602844360,
      "tasks": {
        "total": 2,
        "created": 0,
        "scheduled": 0,
        "deploying": 0,
        "running": 2,
        "finished": 0,
        "canceling": 0,
        "canceled": 0,
        "failed": 0,
        "reconciling": 0,
        "initializing": 0
      }
    },
    {
      "jid": "daf5696c16fc5081c7df056962454254",
      "name": "globalpay_20250408_task",
      "state": "RUNNING",
      "start-time": 1744602894148,
      "end-time": -1,
      "duration": 796633661,
      "last-modification": 1744602909861,
      "tasks": {
        "total": 1,
        "created": 0,
        "scheduled": 0,
        "deploying": 0,
        "running": 1,
        "finished": 0,
        "canceling": 0,
        "canceled": 0,
        "failed": 0,
        "reconciling": 0,
        "initializing": 0
      }
    },
    {
      "jid": "3658f1eb9025d00550c93ff0b03ae654",
      "name": "callback20240819_recharge_task",
      "state": "RUNNING",
      "start-time": 1744602800934,
      "end-time": -1,
      "duration": 796726875,
      "last-modification": 1744602818439,
      "tasks": {
        "total": 4,
        "created": 0,
        "scheduled": 0,
        "deploying": 0,
        "running": 4,
        "finished": 0,
        "canceling": 0,
        "canceled": 0,
        "failed": 0,
        "reconciling": 0,
        "initializing": 0
      }
    },
    {
      "jid": "1f9d78fed1af0929183ceecc5c0c45d3",
      "name": "ta_game_total_job",
      "state": "RUNNING",
      "start-time": 1745282857116,
      "end-time": -1,
      "duration": 116670694,
      "last-modification": 1745282870817,
      "tasks": {
        "total": 18,
        "created": 0,
        "scheduled": 0,
        "deploying": 0,
        "running": 18,
        "finished": 0,
        "canceling": 0,
        "canceled": 0,
        "failed": 0,
        "reconciling": 0,
        "initializing": 0
      }
    },
    {
      "jid": "1ab53e0afa9cf4d96f9bf4ed48fe15be",
      "name": "user_statistics_game_task",
      "state": "RUNNING",
      "start-time": 1744603202836,
      "end-time": -1,
      "duration": 796324973,
      "last-modification": 1744603217218,
      "tasks": {
        "total": 9,
        "created": 0,
        "scheduled": 0,
        "deploying": 0,
        "running": 9,
        "finished": 0,
        "canceling": 0,
        "canceled": 0,
        "failed": 0,
        "reconciling": 0,
        "initializing": 0
      }
    },
    {
      "jid": "126ff4081bd47b2402755ac5e710c3fb",
      "name": "deep_link_task_task",
      "state": "RUNNING",
      "start-time": 1744603422999,
      "end-time": -1,
      "duration": 796104810,
      "last-modification": 1744603432598,
      "tasks": {
        "total": 4,
        "created": 0,
        "scheduled": 0,
        "deploying": 0,
        "running": 4,
        "finished": 0,
        "canceling": 0,
        "canceled": 0,
        "failed": 0,
        "reconciling": 0,
        "initializing": 0
      }
    },
    {
      "jid": "866514769c997836a4bcb990dc68f3b7",
      "name": "teenpatti_task_task",
      "state": "RUNNING",
      "start-time": 1744603049635,
      "end-time": -1,
      "duration": 796478174,
      "last-modification": 1744603057930,
      "tasks": {
        "total": 4,
        "created": 0,
        "scheduled": 0,
        "deploying": 0,
        "running": 4,
        "finished": 0,
        "canceling": 0,
        "canceled": 0,
        "failed": 0,
        "reconciling": 0,
        "initializing": 0
      }
    },
    {
      "jid": "172f00f863adaeea47568aedfdea478e",
      "name": "egg_20250423_task",
      "state": "RUNNING",
      "start-time": 1745287906591,
      "end-time": -1,
      "duration": 111621219,
      "last-modification": 1745287912149,
      "tasks": {
        "total": 6,
        "created": 0,
        "scheduled": 0,
        "deploying": 0,
        "running": 6,
        "finished": 0,
        "canceling": 0,
        "canceled": 0,
        "failed": 0,
        "reconciling": 0,
        "initializing": 0
      }
    },
    {
      "jid": "b44d10c2c5f0390d41a742058a957496",
      "name": "deep_link_first_charge_task",
      "state": "RUNNING",
      "start-time": 1744603275956,
      "end-time": -1,
      "duration": 796251853,
      "last-modification": 1744603279990,
      "tasks": {
        "total": 1,
        "created": 0,
        "scheduled": 0,
        "deploying": 0,
        "running": 1,
        "finished": 0,
        "canceling": 0,
        "canceled": 0,
        "failed": 0,
        "reconciling": 0,
        "initializing": 0
      }
    },
    {
      "jid": "c338f19d5f2195f87e714f277beb7114",
      "name": "new_user_tag_task",
      "state": "RUNNING",
      "start-time": 1744603031552,
      "end-time": -1,
      "duration": 796496258,
      "last-modification": 1744603040235,
      "tasks": {
        "total": 3,
        "created": 0,
        "scheduled": 0,
        "deploying": 0,
        "running": 3,
        "finished": 0,
        "canceling": 0,
        "canceled": 0,
        "failed": 0,
        "reconciling": 0,
        "initializing": 0
      }
    },
    {
      "jid": "e8da455b82c83424f0f5600a992f32eb",
      "name": "doller_20250401_task",
      "state": "RUNNING",
      "start-time": 1744602819750,
      "end-time": -1,
      "duration": 796708059,
      "last-modification": 1744602825937,
      "tasks": {
        "total": 1,
        "created": 0,
        "scheduled": 0,
        "deploying": 0,
        "running": 1,
        "finished": 0,
        "canceling": 0,
        "canceled": 0,
        "failed": 0,
        "reconciling": 0,
        "initializing": 0
      }
    },
    {
      "jid": "5474ea9fadaf315bd2a44f8bc7b08adb",
      "name": "wealth_20250401_prod_task",
      "state": "RUNNING",
      "start-time": 1744603183506,
      "end-time": -1,
      "duration": 796344303,
      "last-modification": 1744603191329,
      "tasks": {
        "total": 3,
        "created": 0,
        "scheduled": 0,
        "deploying": 0,
        "running": 3,
        "finished": 0,
        "canceling": 0,
        "canceled": 0,
        "failed": 0,
        "reconciling": 0,
        "initializing": 0
      }
    },
    {
      "jid": "b61131b3261ed10d7b2fbb3ca92214de",
      "name": "talent_room_month_task",
      "state": "RUNNING",
      "start-time": 1744602781760,
      "end-time": -1,
      "duration": 796746050,
      "last-modification": 1744602796734,
      "tasks": {
        "total": 10,
        "created": 0,
        "scheduled": 0,
        "deploying": 0,
        "running": 10,
        "finished": 0,
        "canceling": 0,
        "canceled": 0,
        "failed": 0,
        "reconciling": 0,
        "initializing": 0
      }
    },
    {
      "jid": "40bf7bec11458c64081d296008b6ec66",
      "name": "teenpatti_box_task",
      "state": "RUNNING",
      "start-time": 1744602761579,
      "end-time": -1,
      "duration": 796766231,
      "last-modification": 1744602778613,
      "tasks": {
        "total": 4,
        "created": 0,
        "scheduled": 0,
        "deploying": 0,
        "running": 4,
        "finished": 0,
        "canceling": 0,
        "canceled": 0,
        "failed": 0,
        "reconciling": 0,
        "initializing": 0
      }
    },
    {
      "jid": "28806f030c100692792b7f77655c8863",
      "name": "oyelite_login_guide_task",
      "state": "RUNNING",
      "start-time": 1744602973894,
      "end-time": -1,
      "duration": 796553916,
      "last-modification": 1744602990673,
      "tasks": {
        "total": 2,
        "created": 0,
        "scheduled": 0,
        "deploying": 0,
        "running": 2,
        "finished": 0,
        "canceling": 0,
        "canceled": 0,
        "failed": 0,
        "reconciling": 0,
        "initializing": 0
      }
    },
    {
      "jid": "624c115c60ea433712b5854a2699dfc8",
      "name": "newbie_tag_task",
      "state": "RUNNING",
      "start-time": 1744602857377,
      "end-time": -1,
      "duration": 796670433,
      "last-modification": 1744602868644,
      "tasks": {
        "total": 3,
        "created": 0,
        "scheduled": 0,
        "deploying": 0,
        "running": 3,
        "finished": 0,
        "canceling": 0,
        "canceled": 0,
        "failed": 0,
        "reconciling": 0,
        "initializing": 0
      }
    },
    {
      "jid": "659150d836c7a3c392603773fb8c8338",
      "name": "talent_room_task",
      "state": "RUNNING",
      "start-time": 1744603127474,
      "end-time": -1,
      "duration": 796400336,
      "last-modification": 1744603140407,
      "tasks": {
        "total": 10,
        "created": 0,
        "scheduled": 0,
        "deploying": 0,
        "running": 10,
        "finished": 0,
        "canceling": 0,
        "canceled": 0,
        "failed": 0,
        "reconciling": 0,
        "initializing": 0
      }
    },
    {
      "jid": "d817b1ed901d2d4586c8fcb2788e67ba",
      "name": "daily_recharge_task",
      "state": "RUNNING",
      "start-time": 1744603331848,
      "end-time": -1,
      "duration": 796195962,
      "last-modification": 1744603337381,
      "tasks": {
        "total": 1,
        "created": 0,
        "scheduled": 0,
        "deploying": 0,
        "running": 1,
        "finished": 0,
        "canceling": 0,
        "canceled": 0,
        "failed": 0,
        "reconciling": 0,
        "initializing": 0
      }
    },
    {
      "jid": "78d8e6079a03a567bd2bad13f3bb4254",
      "name": "inPattern_20250422_task",
      "state": "RUNNING",
      "start-time": 1745200166901,
      "end-time": -1,
      "duration": 199360909,
      "last-modification": 1745200172891,
      "tasks": {
        "total": 3,
        "created": 0,
        "scheduled": 0,
        "deploying": 0,
        "running": 3,
        "finished": 0,
        "canceling": 0,
        "canceled": 0,
        "failed": 0,
        "reconciling": 0,
        "initializing": 0
      }
    },
    {
      "jid": "a3c0714036559318f8145cde55bab7d1",
      "name": "inPattern_20250422_tag_task",
      "state": "RUNNING",
      "start-time": 1745200243952,
      "end-time": -1,
      "duration": 199283858,
      "last-modification": 1745200247921,
      "tasks": {
        "total": 2,
        "created": 0,
        "scheduled": 0,
        "deploying": 0,
        "running": 2,
        "finished": 0,
        "canceling": 0,
        "canceled": 0,
        "failed": 0,
        "reconciling": 0,
        "initializing": 0
      }
    },
    {
      "jid": "3d1bdaab09aabde8276764a75757a288",
      "name": "activity_risk_control",
      "state": "RUNNING",
      "start-time": 1744603887991,
      "end-time": -1,
      "duration": 795639819,
      "last-modification": 1744603896733,
      "tasks": {
        "total": 2,
        "created": 0,
        "scheduled": 0,
        "deploying": 0,
        "running": 2,
        "finished": 0,
        "canceling": 0,
        "canceled": 0,
        "failed": 0,
        "reconciling": 0,
        "initializing": 0
      }
    },
    {
      "jid": "24d00c781cc726911083cbba05a2240b",
      "name": "top_up_gift_package_task",
      "state": "RUNNING",
      "start-time": 1744603239310,
      "end-time": -1,
      "duration": 796288500,
      "last-modification": 1744603243445,
      "tasks": {
        "total": 1,
        "created": 0,
        "scheduled": 0,
        "deploying": 0,
        "running": 1,
        "finished": 0,
        "canceling": 0,
        "canceled": 0,
        "failed": 0,
        "reconciling": 0,
        "initializing": 0
      }
    },
    {
      "jid": "326e1eaf4033ebddc452bfd136f050ad",
      "name": "inTeenPatti_20250417_task",
      "state": "RUNNING",
      "start-time": 1744773847924,
      "end-time": -1,
      "duration": 625679886,
      "last-modification": 1744773853085,
      "tasks": {
        "total": 5,
        "created": 0,
        "scheduled": 0,
        "deploying": 0,
        "running": 5,
        "finished": 0,
        "canceling": 0,
        "canceled": 0,
        "failed": 0,
        "reconciling": 0,
        "initializing": 0
      }
    },
    {
      "jid": "0d840a4728c33a743275e9fe704413cd",
      "name": "user_statistics_consume_task",
      "state": "RUNNING",
      "start-time": 1744603295329,
      "end-time": -1,
      "duration": 796232481,
      "last-modification": 1744603304637,
      "tasks": {
        "total": 10,
        "created": 0,
        "scheduled": 0,
        "deploying": 0,
        "running": 10,
        "finished": 0,
        "canceling": 0,
        "canceled": 0,
        "failed": 0,
        "reconciling": 0,
        "initializing": 0
      }
    },
    {
      "jid": "ec9e1135f5a7c25d608c9f2a7d7317fc",
      "name": "recharge_guide_popup_task",
      "state": "RUNNING",
      "start-time": 1744603221423,
      "end-time": -1,
      "duration": 796306387,
      "last-modification": 1744603226154,
      "tasks": {
        "total": 1,
        "created": 0,
        "scheduled": 0,
        "deploying": 0,
        "running": 1,
        "finished": 0,
        "canceling": 0,
        "canceled": 0,
        "failed": 0,
        "reconciling": 0,
        "initializing": 0
      }
    },
    {
      "jid": "d07d1f72fded614945b5fe66473d9a3a",
      "name": "oyelite_ta_reel_operation_job",
      "state": "RUNNING",
      "start-time": 1745282794032,
      "end-time": -1,
      "duration": 116733778,
      "last-modification": 1745282807760,
      "tasks": {
        "total": 1,
        "created": 0,
        "scheduled": 0,
        "deploying": 0,
        "running": 1,
        "finished": 0,
        "canceling": 0,
        "canceled": 0,
        "failed": 0,
        "reconciling": 0,
        "initializing": 0
      }
    },
    {
      "jid": "27ce5460d181fba8d0196322908235a3",
      "name": "medal_task",
      "state": "FINISHED",
      "start-time": 1744603108010,
      "end-time": 1745396705221,
      "duration": 793597211,
      "last-modification": 1745396705221,
      "tasks": {
        "total": 4,
        "created": 0,
        "scheduled": 0,
        "deploying": 0,
        "running": 0,
        "finished": 4,
        "canceling": 0,
        "canceled": 0,
        "failed": 0,
        "reconciling": 0,
        "initializing": 0
      }
    }
  ]
}